{
  "version": "1.0.0",
  "collected_at": "2026-07-16T06:19:50.905Z",
  "company": {
    "id": "tw-3164-genmont",
    "ticker": "3164",
    "name": "景岳",
    "market": "TWSE",
    "industry_template": "nutrition_health_food"
  },
  "collection_scope": "targeted_research_company",
  "events": [
    {
      "id": "mops-history-3164-1150706-1",
      "date": "2026-07-06",
      "announced_date": "2026-07-06",
      "fact_date": "2026-07-06",
      "announced_time": "17:00:00",
      "title": "公告本公司申請股票上櫃轉上市時所出具之承諾事項 暨其後續執行情形",
      "description": "1.事實發生日:115/07/06 2.公司名稱:景岳生物科技股份有限公司 3.與公司關係(請輸入本公司或子公司):本公司 4.相互持股比例:不適用 5.發生緣由: 依據臺灣證券交易所股份有限公司民國九十九年一月八日臺證上字第0990000468號函 規定辦理，公告本公司股票初次上市時所出具之承諾事項暨其115年度第2季執行情形。 6.因應措施: 承諾本公司各重要子公司之財務報告若係由其他會計師查核簽證，並據以認列投資 損益或編製合併財務報告時，本公司之簽證會計師需對財務報表出具不提及其他會計師 查核意見之報告。 後續執行情形：截至115/6/30為止，本公司並無上述之情事。 7.其他應敘明事項(若事件發生或決議之主體係屬公開發行以上公司，本則重大訊息同時 符合證券交易法施行細則第7條第9款所定對股東權益或證券價格有重大影響之事項):無",
      "clause": "第51款",
      "source_id": "mops_history_api",
      "source_type": "official_history_api",
      "source_url": "https://mops.twse.com.tw/mops/#/web/t05st01?co_id=3164",
      "claim_type": "official_disclosure",
      "review_status": "unreviewed",
      "detail_parameters": {
        "serialNumber": "1",
        "companyId": "3164",
        "marketKind": "sii",
        "enterDate": "1150706"
      }
    },
    {
      "id": "mops-history-3164-1150629-1",
      "date": "2026-06-29",
      "announced_date": "2026-06-29",
      "fact_date": "2026-06-29",
      "announced_time": "10:53:46",
      "title": "公告本公司第五屆薪資報酬委員會委員任期屆滿",
      "description": "1.發生變動日期:115/06/29 2.功能性委員會名稱:薪資報酬委員會 3.舊任者姓名:黃則仁、盧志峰、高志斌 4.舊任者簡歷: (1)黃則仁先生，盛鑫聯合會計師事務所所長。 (2)盧志峰先生，輔仁大學醫學院醫學系助理教授。 (3)高志斌，中央警察大學推廣教育訓練中心講師。 5.新任者姓名:無 6.新任者簡歷:無 7.異動情形（請輸入「辭職」、「解任」、「任期屆滿」、「逝世」或「新任」）: 任期屆滿 8.異動原因:任期屆滿 9.原任期（例xx/xx/xx ~ xx/xx/xx）:112/8/10 ~ 115/06/29 10.新任生效日期:不適用 11.其他應敘明事項:待選任後將另行公告。",
      "clause": "第6款",
      "source_id": "mops_history_api",
      "source_type": "official_history_api",
      "source_url": "https://mops.twse.com.tw/mops/#/web/t05st01?co_id=3164",
      "claim_type": "official_disclosure",
      "review_status": "unreviewed",
      "detail_parameters": {
        "serialNumber": "1",
        "companyId": "3164",
        "marketKind": "sii",
        "enterDate": "1150629"
      }
    },
    {
      "id": "mops-history-3164-1150605-6",
      "date": "2026-06-08",
      "announced_date": "2026-06-08",
      "fact_date": "2026-06-08",
      "announced_time": "15:59:14",
      "title": "公告本公司第三屆審計委員會",
      "description": "1.發生變動日期:115/06/08 2.功能性委員會名稱:審計委員會 3.舊任者姓名:黃則仁，盧志峰，高志斌，林慶隆 4.舊任者簡歷: (1)黃則仁，盛鑫聯合會計師事務所所長。 (2)盧志峰，輔仁大學醫學院醫學系助理教授。 (3)高志斌，景岳生物科技獨董、審計委員及薪酬委員。 (4)林慶隆，慶隆聯合會計師事務所所長。 5.新任者姓名:高志斌，林慶隆，陳仕坤，黃曼瑤 6.新任者簡歷: (1)高志斌，景岳生物科技獨董、審計委員及薪酬委員。 (2)林慶隆，慶隆聯合會計師事務所所長。 (3)陳仕坤，長鋒投資（股）公司董事長。 (4)黃曼瑤，明言律師事務所主持律師。 7.異動情形（請輸入「辭職」、「解任」、「任期屆滿」、「逝世」或「新任」）: 任期屆滿 8.異動原因:任期屆滿。 9.原任期（例xx/xx/xx ~ xx/xx/xx）:112/6/30 ~ 115/06/29 10.新任生效日期:115/06/30 11.其他應敘明事項:無。",
      "clause": "第6款",
      "source_id": "mops_history_api",
      "source_type": "official_history_api",
      "source_url": "https://mops.twse.com.tw/mops/#/web/t05st01?co_id=3164",
      "claim_type": "official_disclosure",
      "review_status": "unreviewed",
      "detail_parameters": {
        "serialNumber": "6",
        "companyId": "3164",
        "marketKind": "sii",
        "enterDate": "1150605"
      }
    },
    {
      "id": "mops-history-3164-1150605-4",
      "date": "2026-06-08",
      "announced_date": "2026-06-08",
      "fact_date": "2026-06-08",
      "announced_time": "15:58:22",
      "title": "公告本公司第十一屆董事長選任",
      "description": "1.董事會決議日期或發生變動日期:115/06/08 2.人員別（請輸入董事長或總經理）:董事長 3.舊任者姓名:陳根德 4.舊任者簡歷:景岳生物科技(股)公司董事長 5.新任者姓名:陳根德 6.新任者簡歷:景岳生物科技(股)公司董事長 7.異動情形（請輸入「辭職」、「解任」、「任期屆滿」、「職務調整」、「資遣」、 「退休」、「逝世」或「新任」）:任期屆滿 8.異動原因:董事改選 9.新任生效日期:115/06/30 10.其他應敘明事項(若事件發生或決議之主體係屬公開發行以上公司，本則重大訊息同時 符合證券交易法施行細則第7條第6款所定對股東權益或證券價格有重大影響之事項):無",
      "clause": "第6款",
      "source_id": "mops_history_api",
      "source_type": "official_history_api",
      "source_url": "https://mops.twse.com.tw/mops/#/web/t05st01?co_id=3164",
      "claim_type": "official_disclosure",
      "review_status": "unreviewed",
      "detail_parameters": {
        "serialNumber": "4",
        "companyId": "3164",
        "marketKind": "sii",
        "enterDate": "1150605"
      }
    },
    {
      "id": "mops-history-3164-1150605-3",
      "date": "2026-06-08",
      "announced_date": "2026-06-08",
      "fact_date": null,
      "announced_time": "15:57:26",
      "title": "公告本公司股東會決議許可董事從事競業行為",
      "description": "",
      "clause": null,
      "source_id": "mops_history_api",
      "source_type": "official_history_api",
      "source_url": "https://mops.twse.com.tw/mops/#/web/t05st01?co_id=3164",
      "claim_type": "official_disclosure",
      "review_status": "unreviewed",
      "detail_parameters": {
        "serialNumber": "3",
        "companyId": "3164",
        "marketKind": "sii",
        "enterDate": "1150605"
      }
    },
    {
      "id": "mops-history-3164-1150605-2",
      "date": "2026-06-08",
      "announced_date": "2026-06-08",
      "fact_date": null,
      "announced_time": "15:56:27",
      "title": "公告本公司董事當選名單(變動達三分之一)",
      "description": "",
      "clause": null,
      "source_id": "mops_history_api",
      "source_type": "official_history_api",
      "source_url": "https://mops.twse.com.tw/mops/#/web/t05st01?co_id=3164",
      "claim_type": "official_disclosure",
      "review_status": "unreviewed",
      "detail_parameters": {
        "serialNumber": "2",
        "companyId": "3164",
        "marketKind": "sii",
        "enterDate": "1150605"
      }
    },
    {
      "id": "mops-history-3164-1150605-7",
      "date": "2026-06-08",
      "announced_date": "2026-06-08",
      "fact_date": null,
      "announced_time": "15:55:09",
      "title": "公告本公司115年股東常會重要決議事項",
      "description": "",
      "clause": null,
      "source_id": "mops_history_api",
      "source_type": "official_history_api",
      "source_url": "https://mops.twse.com.tw/mops/#/web/t05st01?co_id=3164",
      "claim_type": "official_disclosure",
      "review_status": "unreviewed",
      "detail_parameters": {
        "serialNumber": "7",
        "companyId": "3164",
        "marketKind": "sii",
        "enterDate": "1150605"
      }
    },
    {
      "id": "mops-history-3164-1150505-1",
      "date": "2026-05-06",
      "announced_date": "2026-05-06",
      "fact_date": null,
      "announced_time": "14:16:59",
      "title": "公告本公司115年第一季合併財務報告提報董事會",
      "description": "",
      "clause": null,
      "source_id": "mops_history_api",
      "source_type": "official_history_api",
      "source_url": "https://mops.twse.com.tw/mops/#/web/t05st01?co_id=3164",
      "claim_type": "official_disclosure",
      "review_status": "unreviewed",
      "detail_parameters": {
        "serialNumber": "1",
        "companyId": "3164",
        "marketKind": "sii",
        "enterDate": "1150505"
      }
    },
    {
      "id": "mops-history-3164-1150428-1",
      "date": "2026-04-28",
      "announced_date": "2026-04-28",
      "fact_date": null,
      "announced_time": "10:18:51",
      "title": "公告115年第一季財務報告董事會召開日期為115年5月6日",
      "description": "",
      "clause": null,
      "source_id": "mops_history_api",
      "source_type": "official_history_api",
      "source_url": "https://mops.twse.com.tw/mops/#/web/t05st01?co_id=3164",
      "claim_type": "official_disclosure",
      "review_status": "unreviewed",
      "detail_parameters": {
        "serialNumber": "1",
        "companyId": "3164",
        "marketKind": "sii",
        "enterDate": "1150428"
      }
    },
    {
      "id": "mops-history-3164-1150407-1",
      "date": "2026-04-07",
      "announced_date": "2026-04-07",
      "fact_date": null,
      "announced_time": "17:19:30",
      "title": "公告本公司申請股票上櫃轉上市時所出具之承諾事項 暨其後續執行情形",
      "description": "",
      "clause": null,
      "source_id": "mops_history_api",
      "source_type": "official_history_api",
      "source_url": "https://mops.twse.com.tw/mops/#/web/t05st01?co_id=3164",
      "claim_type": "official_disclosure",
      "review_status": "unreviewed",
      "detail_parameters": {
        "serialNumber": "1",
        "companyId": "3164",
        "marketKind": "sii",
        "enterDate": "1150407"
      }
    },
    {
      "id": "mops-history-3164-1150309-1",
      "date": "2026-03-09",
      "announced_date": "2026-03-09",
      "fact_date": null,
      "announced_time": "14:46:40",
      "title": "公告本公司訂定除息基準日",
      "description": "",
      "clause": null,
      "source_id": "mops_history_api",
      "source_type": "official_history_api",
      "source_url": "https://mops.twse.com.tw/mops/#/web/t05st01?co_id=3164",
      "claim_type": "official_disclosure",
      "review_status": "unreviewed",
      "detail_parameters": {
        "serialNumber": "1",
        "companyId": "3164",
        "marketKind": "sii",
        "enterDate": "1150309"
      }
    },
    {
      "id": "mops-history-3164-1150309-2",
      "date": "2026-03-09",
      "announced_date": "2026-03-09",
      "fact_date": null,
      "announced_time": "14:46:16",
      "title": "公告本公司董事會114年度每普通股配發現金股利0.8元",
      "description": "",
      "clause": null,
      "source_id": "mops_history_api",
      "source_type": "official_history_api",
      "source_url": "https://mops.twse.com.tw/mops/#/web/t05st01?co_id=3164",
      "claim_type": "official_disclosure",
      "review_status": "unreviewed",
      "detail_parameters": {
        "serialNumber": "2",
        "companyId": "3164",
        "marketKind": "sii",
        "enterDate": "1150309"
      }
    },
    {
      "id": "mops-history-3164-1150306-3",
      "date": "2026-03-09",
      "announced_date": "2026-03-09",
      "fact_date": null,
      "announced_time": "14:32:21",
      "title": "公告本公司114年第四季合併財務報告提報董事會",
      "description": "",
      "clause": null,
      "source_id": "mops_history_api",
      "source_type": "official_history_api",
      "source_url": "https://mops.twse.com.tw/mops/#/web/t05st01?co_id=3164",
      "claim_type": "official_disclosure",
      "review_status": "unreviewed",
      "detail_parameters": {
        "serialNumber": "3",
        "companyId": "3164",
        "marketKind": "sii",
        "enterDate": "1150306"
      }
    },
    {
      "id": "mops-history-3164-1150306-2",
      "date": "2026-03-09",
      "announced_date": "2026-03-09",
      "fact_date": null,
      "announced_time": "14:25:09",
      "title": "公告本公司董事會決議通過114年度董事及員工酬勞分派",
      "description": "",
      "clause": null,
      "source_id": "mops_history_api",
      "source_type": "official_history_api",
      "source_url": "https://mops.twse.com.tw/mops/#/web/t05st01?co_id=3164",
      "claim_type": "official_disclosure",
      "review_status": "unreviewed",
      "detail_parameters": {
        "serialNumber": "2",
        "companyId": "3164",
        "marketKind": "sii",
        "enterDate": "1150306"
      }
    },
    {
      "id": "mops-history-3164-1150306-1",
      "date": "2026-03-09",
      "announced_date": "2026-03-09",
      "fact_date": null,
      "announced_time": "14:20:52",
      "title": "公告本公司董事會決議召開115年股東常會相關事宜",
      "description": "",
      "clause": null,
      "source_id": "mops_history_api",
      "source_type": "official_history_api",
      "source_url": "https://mops.twse.com.tw/mops/#/web/t05st01?co_id=3164",
      "claim_type": "official_disclosure",
      "review_status": "unreviewed",
      "detail_parameters": {
        "serialNumber": "1",
        "companyId": "3164",
        "marketKind": "sii",
        "enterDate": "1150306"
      }
    },
    {
      "id": "mops-history-3164-1150226-1",
      "date": "2026-02-26",
      "announced_date": "2026-02-26",
      "fact_date": null,
      "announced_time": "16:32:57",
      "title": "公告114年第四季財務報告董事會召開日期為115年3月9日",
      "description": "",
      "clause": null,
      "source_id": "mops_history_api",
      "source_type": "official_history_api",
      "source_url": "https://mops.twse.com.tw/mops/#/web/t05st01?co_id=3164",
      "claim_type": "official_disclosure",
      "review_status": "unreviewed",
      "detail_parameters": {
        "serialNumber": "1",
        "companyId": "3164",
        "marketKind": "sii",
        "enterDate": "1150226"
      }
    },
    {
      "id": "mops-history-3164-1150105-1",
      "date": "2026-01-05",
      "announced_date": "2026-01-05",
      "fact_date": null,
      "announced_time": "17:17:21",
      "title": "公告本公司申請股票上櫃轉上市時所出具之承諾事項 暨其後續執行情形",
      "description": "",
      "clause": null,
      "source_id": "mops_history_api",
      "source_type": "official_history_api",
      "source_url": "https://mops.twse.com.tw/mops/#/web/t05st01?co_id=3164",
      "claim_type": "official_disclosure",
      "review_status": "unreviewed",
      "detail_parameters": {
        "serialNumber": "1",
        "companyId": "3164",
        "marketKind": "sii",
        "enterDate": "1150105"
      }
    },
    {
      "id": "mops-history-3164-1141107-1",
      "date": "2025-11-11",
      "announced_date": "2025-11-11",
      "fact_date": null,
      "announced_time": "14:20:13",
      "title": "公告本公司114年第三季合併財務報告提報董事會",
      "description": "",
      "clause": null,
      "source_id": "mops_history_api",
      "source_type": "official_history_api",
      "source_url": "https://mops.twse.com.tw/mops/#/web/t05st01?co_id=3164",
      "claim_type": "official_disclosure",
      "review_status": "unreviewed",
      "detail_parameters": {
        "serialNumber": "1",
        "companyId": "3164",
        "marketKind": "sii",
        "enterDate": "1141107"
      }
    },
    {
      "id": "mops-history-3164-1141103-1",
      "date": "2025-11-03",
      "announced_date": "2025-11-03",
      "fact_date": null,
      "announced_time": "14:19:40",
      "title": "公告114年第三季財務報告董事會召開日期為114年11月11日",
      "description": "",
      "clause": null,
      "source_id": "mops_history_api",
      "source_type": "official_history_api",
      "source_url": "https://mops.twse.com.tw/mops/#/web/t05st01?co_id=3164",
      "claim_type": "official_disclosure",
      "review_status": "unreviewed",
      "detail_parameters": {
        "serialNumber": "1",
        "companyId": "3164",
        "marketKind": "sii",
        "enterDate": "1141103"
      }
    },
    {
      "id": "mops-history-3164-1141002-1",
      "date": "2025-10-02",
      "announced_date": "2025-10-02",
      "fact_date": null,
      "announced_time": "16:28:16",
      "title": "公告本公司申請股票上櫃轉上市時所出具之承諾事項 暨其後續執行情形",
      "description": "",
      "clause": null,
      "source_id": "mops_history_api",
      "source_type": "official_history_api",
      "source_url": "https://mops.twse.com.tw/mops/#/web/t05st01?co_id=3164",
      "claim_type": "official_disclosure",
      "review_status": "unreviewed",
      "detail_parameters": {
        "serialNumber": "1",
        "companyId": "3164",
        "marketKind": "sii",
        "enterDate": "1141002"
      }
    },
    {
      "id": "mops-history-3164-1140925-1",
      "date": "2025-09-25",
      "announced_date": "2025-09-25",
      "fact_date": null,
      "announced_time": "15:08:54",
      "title": "本公司受邀參加法人說明會",
      "description": "",
      "clause": null,
      "source_id": "mops_history_api",
      "source_type": "official_history_api",
      "source_url": "https://mops.twse.com.tw/mops/#/web/t05st01?co_id=3164",
      "claim_type": "official_disclosure",
      "review_status": "unreviewed",
      "detail_parameters": {
        "serialNumber": "1",
        "companyId": "3164",
        "marketKind": "sii",
        "enterDate": "1140925"
      }
    },
    {
      "id": "mops-history-3164-1140826-2",
      "date": "2025-08-26",
      "announced_date": "2025-08-26",
      "fact_date": null,
      "announced_time": "13:49:50",
      "title": "公告本公司註銷庫藏股減資辦理資本變更登記完成",
      "description": "",
      "clause": null,
      "source_id": "mops_history_api",
      "source_type": "official_history_api",
      "source_url": "https://mops.twse.com.tw/mops/#/web/t05st01?co_id=3164",
      "claim_type": "official_disclosure",
      "review_status": "unreviewed",
      "detail_parameters": {
        "serialNumber": "2",
        "companyId": "3164",
        "marketKind": "sii",
        "enterDate": "1140826"
      }
    },
    {
      "id": "mops-history-3164-1140808-2",
      "date": "2025-08-08",
      "announced_date": "2025-08-08",
      "fact_date": null,
      "announced_time": "14:08:58",
      "title": "公告本公司董事會決議註銷庫藏股及訂定減資基準日",
      "description": "",
      "clause": null,
      "source_id": "mops_history_api",
      "source_type": "official_history_api",
      "source_url": "https://mops.twse.com.tw/mops/#/web/t05st01?co_id=3164",
      "claim_type": "official_disclosure",
      "review_status": "unreviewed",
      "detail_parameters": {
        "serialNumber": "2",
        "companyId": "3164",
        "marketKind": "sii",
        "enterDate": "1140808"
      }
    },
    {
      "id": "mops-history-3164-1140808-1",
      "date": "2025-08-08",
      "announced_date": "2025-08-08",
      "fact_date": null,
      "announced_time": "14:01:59",
      "title": "公告本公司114年第二季合併財務報告提報董事會",
      "description": "",
      "clause": null,
      "source_id": "mops_history_api",
      "source_type": "official_history_api",
      "source_url": "https://mops.twse.com.tw/mops/#/web/t05st01?co_id=3164",
      "claim_type": "official_disclosure",
      "review_status": "unreviewed",
      "detail_parameters": {
        "serialNumber": "1",
        "companyId": "3164",
        "marketKind": "sii",
        "enterDate": "1140808"
      }
    }
  ],
  "references": [
    {
      "id": "mops-history-3164",
      "title": "景岳 MOPS 歷史重大訊息",
      "url": "https://mops.twse.com.tw/mops/#/web/t05st01?co_id=3164",
      "source_id": "mops_history_search",
      "source_type": "official_history_api",
      "claim_type": "official_search_reference",
      "review_status": "reference_only",
      "note": "以公開資訊觀測站歷史重大訊息 API 依公司代號與民國年度蒐集，保留查詢頁來源與詳細資料欄位。"
    },
    {
      "id": "company-website-3164",
      "title": "景岳 官方網站",
      "url": "https://www.genmont.com.tw/",
      "source_id": "company_website",
      "source_type": "company_reference",
      "claim_type": "company_published_reference",
      "review_status": "reference_only",
      "note": "保留公司自行揭露頁面的來源連結；未經欄位驗證的內容不直接視為客觀事實。"
    }
  ],
  "source_status": [
    {
      "source_id": "twse_material_events",
      "cache_status": "fresh",
      "fetched_at": "2026-07-16T06:19:38.979Z",
      "row_count": 87,
      "available": true
    },
    {
      "source_id": "mops_history_api",
      "cache_status": "fresh",
      "fetched_at": "2026-07-16T05:37:52.273Z",
      "row_count": 42,
      "detail_count": 4,
      "available": true
    }
  ],
  "limitations": [
    "官方交易所重大訊息快取為近期資料；歷史範圍應透過 MOPS 歷史查詢頁覆核。",
    "公司網站連結僅為研究參考，未經欄位驗證的內容不直接納入評分。",
    "事件保留原始公告文字摘要，不代表投資建議或系統判定。"
  ]
}
